LICENSE
MANIFEST.in
README.md
setup.py
src/aeroport/__init__.py
src/aeroport/__main__.py
src/aeroport/abc.py
src/aeroport/db.py
src/aeroport/dispatch.py
src/aeroport/management.py
src/aeroport/payload.py
src/aeroport/proxy.py
src/aeroport/scraping.py
src/aeroport/yml.py
src/aeroport.egg-info/PKG-INFO
src/aeroport.egg-info/SOURCES.txt
src/aeroport.egg-info/dependency_links.txt
src/aeroport.egg-info/entry_points.txt
src/aeroport.egg-info/not-zip-safe
src/aeroport.egg-info/requires.txt
src/aeroport.egg-info/top_level.txt
src/aeroport/airlines/__init__.py
src/aeroport/airlines/air_example/__init__.py
src/aeroport/airlines/air_example/payload.py
src/aeroport/airlines/air_example/registration.py
src/aeroport/airlines/air_example/origins/__init__.py
src/aeroport/airlines/air_example/origins/github.py
src/aeroport/cli/__init__.py
src/aeroport/cli/commands.py
src/aeroport/destinations/__init__.py
src/aeroport/destinations/console.py
src/aeroport/destinations/stream.py
src/aeroport/settings/__init__.py
src/aeroport/settings/base.py
src/aeroport/settings/develop.py
src/aeroport/web/__init__.py
src/aeroport/web/server.py
src/aeroport/web/rest/__init__.py
src/aeroport/web/rest/urls.py
src/aeroport/web/rest/views/__init__.py
src/aeroport/web/rest/views/airlines.py
src/aeroport/web/rest/views/flights.py
src/aeroport/web/rest/views/generic.py