Metadata-Version: 1.1
Name: aeroport
Version: 0.0.2
Summary: Organize hub for data arrival / departures
Home-page: https://github.com/anti1869/aeroport
Author: Dmitry Litvinenko
Author-email: anti1869@gmail.com
License: Apache 2
Platform: UNKNOWN
Classifier: License :: OSI Approved :: Apache Software License
Classifier: Intended Audience :: Developers
Classifier: Programming Language :: Python
Classifier: Programming Language :: Python :: 3
Classifier: Programming Language :: Python :: 3.5
Classifier: Topic :: Internet :: WWW/HTTP
Classifier: Development Status :: 2 - Pre-Alpha
